setup.py
runge_kutt/__init__.py
runge_kutt/functions.py
runge_kutt.egg-info/PKG-INFO
runge_kutt.egg-info/SOURCES.txt
runge_kutt.egg-info/dependency_links.txt
runge_kutt.egg-info/not-zip-safe
runge_kutt.egg-info/top_level.txt