Metadata-Version: 1.0
Name: runge-kutt
Version: 0.1
Summary: A differential equation solving algorithm implementation
Home-page: http://github.com/Icebreaker454/runge_kutt
Author: Paul Pukach a.k.a. Icebreaker
Author-email: pavlopukach@gmail.com
License: MIT
Platform: UNKNOWN
